pywalletconnect/__init__.py
pywalletconnect/base58.py
pywalletconnect/client.py
pywalletconnect/client_v1.py
pywalletconnect/client_v2irn.py
pywalletconnect/client_v2waku.py
pywalletconnect/enc_tunnel.py
pywalletconnect/json_rpc.py
pywalletconnect/tls_socket.py
pywalletconnect/version.py
pywalletconnect/websocket.py
pywalletconnect/ws_auth.py
pyWalletConnect-1.6.2.dist-info/LICENSE
pyWalletConnect-1.6.2.dist-info/METADATA
pyWalletConnect-1.6.2.dist-info/WHEEL
pyWalletConnect-1.6.2.dist-info/top_level.txt
pyWalletConnect-1.6.2.dist-info/RECORD
