Metadata-Version: 2.1
Name: pyWalletConnect
Version: 1.6.2
Summary: WalletConnect implementation for Python wallets
Home-page: https://github.com/bitlogik/pyWalletConnect
Author: BitLogiK
Author-email: contact@bitlogik.fr
License: GPLv3
Keywords: blockchain wallet cryptography security
Classifier: Programming Language :: Python :: 3 :: Only
Classifier: License :: OSI Approved :: GNU General Public License v3 (GPLv3)
Classifier: Development Status :: 5 - Production/Stable
Classifier: Intended Audience :: Developers
Classifier: Intended Audience :: Information Technology
Classifier: Intended Audience :: System Administrators
Classifier: Intended Audience :: Telecommunications Industry
Classifier: Topic :: Security :: Cryptography
Classifier: Topic :: Software Development :: Libraries :: Python Modules
Requires-Python: >=3.7
License-File: LICENSE
Requires-Dist: cryptography >=3.3
Requires-Dist: wsproto >=1.0.0
